GDriveOps/GDhandler.py
GDriveOps/__init__.py
tests/__init__.py
tests/test_gdhandler.py
GDriveOps-0.3.5.dist-info/LICENSE
GDriveOps-0.3.5.dist-info/METADATA
GDriveOps-0.3.5.dist-info/WHEEL
GDriveOps-0.3.5.dist-info/dependency_links.txt
GDriveOps-0.3.5.dist-info/entry_points.txt
GDriveOps-0.3.5.dist-info/top_level.txt
GDriveOps-0.3.5.dist-info/RECORD
