Metadata-Version: 2.1
Name: GDriveOps
Version: 0.3.5
Summary: A package for handling Google Drive file operations
Home-page: https://github.com/drhammed/GDriveOps
Author: Hammed A. Akande
Author-email: "Hammed A. Akande" <akandehammedadedamola@gmail.com>
Project-URL: homepage, https://github.com/drhammed/GDriveOps
Project-URL: repository, https://github.com/drhammed/GDriveOps
Project-URL: issues, https://github.com/drhammed/GDriveOps/issues
Classifier: Development Status :: 3 - Alpha
Classifier: Intended Audience :: Developers
Classifier: Programming Language :: Python :: 3
Classifier: License :: OSI Approved :: MIT License
Classifier: Operating System :: OS Independent
Requires-Python: >=3.6
License-File: LICENSE
Requires-Dist: google-api-python-client
Requires-Dist: google-auth
Requires-Dist: google-auth-httplib2
Requires-Dist: google-auth-oauthlib
Requires-Dist: PyMuPDF
Requires-Dist: python-docx
Provides-Extra: dev
Requires-Dist: pytest; extra == "dev"
Requires-Dist: pytest-cov; extra == "dev"
